guillotina_rediscache/__init__.py
guillotina_rediscache/api.py
guillotina_rediscache/cache.py
guillotina_rediscache/cache_strategy.py
guillotina_rediscache/files.py
guillotina_rediscache/interfaces.py
guillotina_rediscache/lru.c
guillotina_rediscache/lru.cpython-36m-darwin.so
guillotina_rediscache/serialize.py
guillotina_rediscache/utility.py
guillotina_rediscache/tests/__init__.py
guillotina_rediscache/tests/conftest.py
guillotina_rediscache/tests/fixtures.py
guillotina_rediscache/tests/lru_bench.py
guillotina_rediscache/tests/lru_memory_track.py
guillotina_rediscache/tests/test_cache.py
guillotina_rediscache/tests/test_lru.py
guillotina_rediscache-2.1.1.dist-info/METADATA
guillotina_rediscache-2.1.1.dist-info/RECORD
guillotina_rediscache-2.1.1.dist-info/WHEEL
guillotina_rediscache-2.1.1.dist-info/top_level.txt
guillotina_rediscache-2.1.1.dist-info/zip-safe
measures/__init__.py
measures/config.yaml
measures/configuration.py
measures/serialize.py
measures/speed_create.py
measures/speed_get.py
measures/speed_modify.py
