Metadata-Version: 2.1
Name: guillotina-rediscache
Version: 2.1.1
Summary: guillotina cache implementation using redis + lru in-memory cache
Home-page: https://github.com/guillotinaweb/guillotina_rediscache
Author: Nathan Van Gheem
Author-email: vangheem@gmail.com
License: BSD
Keywords: asyncio,REST,guillotina,cache,redis
Platform: UNKNOWN
Classifier: License :: OSI Approved :: BSD License
Classifier: Development Status :: 3 - Alpha
Classifier: Intended Audience :: Developers
Classifier: Topic :: Internet :: WWW/HTTP
Classifier: Programming Language :: Python :: 3.6
Classifier: Topic :: Software Development :: Libraries :: Python Modules
Provides-Extra: test
Requires-Dist: guillotina (>=4.3.2)
Requires-Dist: aioredis (>=1.0.0)
Requires-Dist: ujson
Provides-Extra: test
Requires-Dist: pytest; extra == 'test'
Requires-Dist: pytest-benchmark; extra == 'test'
Requires-Dist: lru-dict; extra == 'test'
Requires-Dist: docker; extra == 'test'
Requires-Dist: backoff; extra == 'test'
Requires-Dist: pytest-asyncio; extra == 'test'
Requires-Dist: pytest-aiohttp; extra == 'test'
Requires-Dist: pytest-cov; extra == 'test'
Requires-Dist: pytest-docker-fixtures (>=1.1.0); extra == 'test'
